mangrove/__init__.py
mangrove/editorDefinitions
mangrove/jokes.txt
mangrove/mangrove-firebase.sdk
mangrove/markdown.py
mangrove/mgvApi.py
mangrove/mgvCom.py
mangrove/mgvTextEditor.py
mangrove/mgvUI.py
mangrove/mgvWrapperMongo.py
mangrove/mgvWrapperNeo4j.py
mangrove/mgvWrapperNoServer.py
mangrove/style.css
mangrove/UI/action.ui
mangrove/UI/createGraph.ui
mangrove/UI/editor.ui
mangrove/UI/envEditor.ui
mangrove/UI/groupEditor.ui
mangrove/UI/huds.ui
mangrove/UI/localSettings.ui
mangrove/UI/login.ui
mangrove/UI/macro.ui
mangrove/UI/main.ui
mangrove/UI/mgvSplash.png
mangrove/UI/mgvSplash.svg
mangrove/UI/pattern.ui
mangrove/UI/projectSettings.ui
mangrove/UI/recap.ui
mangrove/UI/rename.ui
mangrove/UI/share.ui
mangrove/UI/transfert.ui
mangrove/UI/type.ui
mangrove/UI/typeFile.ui
mangrove/UI/var.ui
mangrove/UI/welcome.ui
mangrove/fonts/Crescent-Regular.ttf
mangrove/fonts/Heebo-Black.ttf
mangrove/fonts/Heebo-Bold.ttf
mangrove/fonts/Heebo-ExtraBold.ttf
mangrove/fonts/Heebo-Light.ttf
mangrove/fonts/Heebo-Medium.ttf
mangrove/fonts/Heebo-Regular.ttf
mangrove/fonts/Heebo-Thin.ttf
mangrove/fonts/OFL.txt
mangrove/icons/arrow-down.svg
mangrove/icons/arrow-left-circle.svg
mangrove/icons/arrow-right-circle.svg
mangrove/icons/arrow-up.svg
mangrove/icons/check-circle.svg
mangrove/icons/check-square-grey.svg
mangrove/icons/check-square-orange.svg
mangrove/icons/check-square.svg
mangrove/icons/chevron-down-blue.svg
mangrove/icons/chevron-down.svg
mangrove/icons/chevron-up-blue.svg
mangrove/icons/chevron-up.svg
mangrove/icons/circle.svg
mangrove/icons/edit-3-white.svg
mangrove/icons/edit-3.svg
mangrove/icons/eye-blue.svg
mangrove/icons/eye.svg
mangrove/icons/flag.svg
mangrove/icons/folder.svg
mangrove/icons/hash.png
mangrove/icons/info.svg
mangrove/icons/lock.svg
mangrove/icons/maximize.svg
mangrove/icons/mgv.ico
mangrove/icons/mgvIcon.svg
mangrove/icons/mgvIconG.svg
mangrove/icons/more-horizontal.svg
mangrove/icons/more-vertical.svg
mangrove/icons/plus-white.svg
mangrove/icons/plus.svg
mgv-1.2.2.dist-info/METADATA
mgv-1.2.2.dist-info/WHEEL
mgv-1.2.2.dist-info/top_level.txt
mgv-1.2.2.dist-info/RECORD
