Metadata-Version: 2.1
Name: mgv
Version: 1.2.2
Summary: An open-source nodal pipeline manager
Home-page: https://gitlab.com/TheYardVFX/mangrove
Author: Bekri Djelloul
Author-email: mangrove@theyard-vfx.com
License: LGPL v3
Platform: UNKNOWN
Requires-Dist: xlrd
Requires-Dist: Qt.py
Requires-Dist: pymongo
Requires-Dist: PySide ; python_version<'3.0'
Requires-Dist: PySide2 ; python_version>='3.0'
